prio/__init__.py
prio/_libprio.cpython-36m-darwin.so
prio/libprio.py
prio-1.1.dist-info/METADATA
prio-1.1.dist-info/WHEEL
prio-1.1.dist-info/top_level.txt
prio-1.1.dist-info/RECORD
