Metadata-Version: 2.1
Name: prio
Version: 1.1
Summary: An interface to libprio
Home-page: https://github.com/mozilla/libprio
Author: Anthony Miyaguchi
Author-email: amiyaguchi@mozilla.com
License: UNKNOWN
Platform: UNKNOWN
